{
  "id": 23423424,
  "idea": "my business idea1",
  "description": "description2",
  "questions": {
    "question1": "question1",
    "question2": "question2",
    "question3": "question3",
    "question4": "question4",
    "question5": "question5",
    "question6": "question6"
  }
}
{
  "id": 2432342345,
  "idea": "my business idea2",
  "description": "description2",
  "questions": {
    "question1": "question1",
    "question2": "question2",
    "question3": "question3",
    "question4": "question4",
    "question5": "question5",
    "question6": "question6"
  }
}

{
  "id": 24323423453,
  "idea": "my business idea3",
  "description": "description3",
  "questions": {
    "question1": "question1",
    "question2": "question2",
    "question3": "question3",
    "question4": "question4",
    "question5": "question5",
    "question6": "question6"
  }
}
